wikirec/__init__.py
wikirec/data_utils.py
wikirec/languages.py
wikirec/model.py
wikirec/utils.py
wikirec-1.0.1.dist-info/LICENSE.txt
wikirec-1.0.1.dist-info/METADATA
wikirec-1.0.1.dist-info/WHEEL
wikirec-1.0.1.dist-info/top_level.txt
wikirec-1.0.1.dist-info/RECORD
