Metadata-Version: 2.1
Name: wikirec
Version: 1.0.1
Summary: Recommendation engine framework based on Wikipedia data
Home-page: https://github.com/andrewtavis/wikirec
Author: Andrew Tavis McAllister
Author-email: andrew.t.mcallister@gmail.com
License: new BSD
Platform: UNKNOWN
Classifier: Development Status :: 5 - Production/Stable
Classifier: Intended Audience :: Developers
Classifier: Intended Audience :: Education
Classifier: Intended Audience :: Science/Research
Classifier: License :: OSI Approved :: BSD License
Classifier: Programming Language :: Python
Classifier: Programming Language :: Python :: 3
Classifier: Programming Language :: Python :: 3.6
Classifier: Programming Language :: Python :: 3.7
Classifier: Programming Language :: Python :: 3.8
Classifier: Operating System :: OS Independent
Requires-Dist: pytest-cov
Requires-Dist: numpy
Requires-Dist: pandas
Requires-Dist: nltk
Requires-Dist: spacy
Requires-Dist: stopwordsiso
Requires-Dist: matplotlib
Requires-Dist: seaborn
Requires-Dist: gensim
Requires-Dist: scikit-learn
Requires-Dist: keras
Requires-Dist: sentence-transformers
Requires-Dist: tensorflow
Requires-Dist: tqdm
Requires-Dist: beautifulsoup4
Requires-Dist: mwparserfromhell
Requires-Dist: defusedxml
